{
  "protocol": "TLZ/1.0",
  "rfc": "TLZ - TLS with ZK Witnessing and P2P Shared HME",
  "timestamp": "2026-02-01T15:52:11Z",
  "token": "DD87KkJH3hJeTC8U3msdrbzwkApmjDrxXA3sTbC7FAKE",
  "shard": 14,
  "osi_layers": {
    "layer_4_transport": "TLS/1.3",
    "layer_5_session": "TLZ session binding",
    "layer_6_presentation": "cRDFa compression",
    "layer_7_application": "HME metadata exchange"
  },
  "tlz_handshake": {
    "client_hello": {
      "caps": {
        "zk_suites": ["bulletproofs", "zkSNARK"],
        "hme_params": ["additive", "leveled-fhe"],
        "crdfa_profiles": ["v1"]
      }
    },
    "server_hello": {
      "chosen": {
        "zk": "bulletproofs",
        "hme": "additive",
        "crdfa": "v1"
      }
    },
    "zk_request": {
      "predicate": "token-holder:DD87KkJH3hJeTC8U3msdrbzwkApmjDrxXA3sTbC7FAKE"
    },
    "zk_proof": {
      "witness_scheme_id": 1,
      "binding_token": "e63fcc84a5be4c7a368fa31ec9bd6990f01131ba419b0d542317e1daf072978e",
      "proof_data": "witness_generated_by_9muses"
    }
  },
  "urls_witnessed": [
    "https://solscan.io/token/DD87KkJH3hJeTC8U3msdrbzwkApmjDrxXA3sTbC7FAKE",
    "https://solscan.io",
    "https://pump.fun",
    "https://pump.fun/coin/DD87KkJH3hJeTC8U3msdrbzwkApmjDrxXA3sTbC7FAKE"
  ],
  "crdfa_metadata": {
    "file": "witnesses/crdfa/DD87KkJH3hJeTC8U3msdrbzwkApmjDrxXA3sTbC7FAKE.crdfa",
    "format": "application/c-rdfa",
    "compression": "gzip",
    "triples": 0
  },
  "hme_operations": {
    "encrypted_metadata": "witnesses/hme/DD87KkJH3hJeTC8U3msdrbzwkApmjDrxXA3sTbC7FAKE_hme.enc",
    "operations": ["HME_META_PUT", "HME_META_QUERY"],
    "homomorphic_scheme": "additive"
  },
  "perf_capture": {
    "file": "witnesses/sessions/DD87KkJH3hJeTC8U3msdrbzwkApmjDrxXA3sTbC7FAKE_tlz.perf",
    "size": 0
  }
}
